{
  "chapters": {
    "1": {
      "pendingViews": 11,
      "lastIncrement": "2025-12-09T19:33:06.088Z",
      "lastUpdate": "2025-12-09T00:15:58+07:00"
    },
    "2": {
      "pendingViews": 5,
      "lastIncrement": "2025-12-09T19:33:57.616Z",
      "lastUpdate": "2025-12-09T00:15:58+07:00"
    },
    "3": {
      "pendingViews": 8,
      "lastIncrement": "2025-12-09T19:35:55.772Z",
      "lastUpdate": "2025-12-09T00:15:58+07:00"
    },
    "4": {
      "pendingViews": 7,
      "lastIncrement": "2025-12-09T19:38:51.072Z",
      "lastUpdate": "2025-12-09T00:15:58+07:00"
    },
    "5": {
      "pendingViews": 9,
      "lastIncrement": "2025-12-09T19:39:42.975Z",
      "lastUpdate": "2025-12-09T00:15:58+07:00"
    },
    "6": {
      "pendingViews": 12,
      "lastIncrement": "2025-12-09T19:39:59.714Z",
      "lastUpdate": "2025-12-09T00:15:58+07:00"
    },
    "7": {
      "pendingViews": 15,
      "lastIncrement": "2025-12-09T19:38:48.252Z",
      "lastUpdate": "2025-12-09T00:15:58+07:00"
    },
    "8": {
      "pendingViews": 30,
      "lastIncrement": "2025-12-09T19:29:28.385Z",
      "lastUpdate": "2025-12-09T00:15:58+07:00"
    },
    "9": {
      "pendingViews": 125,
      "lastIncrement": "2025-12-09T19:39:40.790Z"
    }
  },
  "lastUpdated": "2025-12-09T00:15:58+07:00"
}