{
  "chapters": {
    "1": {
      "pendingViews": 1,
      "lastIncrement": "2026-01-20T04:51:30.993Z",
      "lastUpdate": "2026-01-20T00:19:54+07:00"
    },
    "2": {
      "pendingViews": 1,
      "lastIncrement": "2026-01-20T04:54:56.005Z",
      "lastUpdate": "2026-01-20T00:19:54+07:00"
    },
    "3": {
      "pendingViews": 1,
      "lastIncrement": "2026-01-20T04:57:07.499Z",
      "lastUpdate": "2026-01-20T00:19:54+07:00"
    },
    "4": {
      "pendingViews": 1,
      "lastIncrement": "2026-01-20T04:59:14.546Z",
      "lastUpdate": "2026-01-20T00:19:54+07:00"
    },
    "5": {
      "pendingViews": 0,
      "lastIncrement": "2026-01-18T23:18:05.476Z",
      "lastUpdate": "2026-01-20T00:19:54+07:00"
    },
    "6": {
      "pendingViews": 0,
      "lastIncrement": "2026-01-18T23:19:15.436Z",
      "lastUpdate": "2026-01-20T00:19:54+07:00"
    },
    "7": {
      "pendingViews": 0,
      "lastIncrement": "2026-01-18T23:20:21.432Z",
      "lastUpdate": "2026-01-20T00:19:54+07:00"
    },
    "8": {
      "pendingViews": 0,
      "lastIncrement": "2026-01-18T23:21:40.170Z",
      "lastUpdate": "2026-01-20T00:19:54+07:00"
    },
    "9": {
      "pendingViews": 1,
      "lastIncrement": "2026-01-19T23:33:25.410Z",
      "lastUpdate": "2026-01-20T00:19:54+07:00"
    },
    "10": {
      "pendingViews": 2,
      "lastIncrement": "2026-01-20T03:09:22.688Z",
      "lastUpdate": "2026-01-20T00:19:54+07:00"
    }
  },
  "lastUpdated": "2026-01-09T00:23:01+07:00"
}